losscape/__init__.py
losscape/compute_loss.py
losscape/create_directions.py
losscape/create_landscape.py
losscape/train.py
losscape-1.5.10.dist-info/METADATA
losscape-1.5.10.dist-info/WHEEL
losscape-1.5.10.dist-info/top_level.txt
losscape-1.5.10.dist-info/RECORD
