Metadata-Version: 2.1
Name: losscape
Version: 1.5.10
Summary: Visualize easily the loss landscape of your neural networks
Home-page: https://github.com/Procuste34/losscape
Author: Alexandre TL
Author-email: alexandretl3434@gmail.com
Requires-Dist: torch (>=1.8.1)
Requires-Dist: numpy
Requires-Dist: scipy
Requires-Dist: matplotlib
Requires-Dist: h5py
